astro_airflow_mcp/__init__.py
astro_airflow_mcp/__main__.py
astro_airflow_mcp/adapter_manager.py
astro_airflow_mcp/auth.py
astro_airflow_mcp/constants.py
astro_airflow_mcp/logging.py
astro_airflow_mcp/models.py
astro_airflow_mcp/plugin.py
astro_airflow_mcp/prompts.py
astro_airflow_mcp/resources.py
astro_airflow_mcp/server.py
astro_airflow_mcp/utils.py
astro_airflow_mcp/adapters/__init__.py
astro_airflow_mcp/adapters/airflow_v2.py
astro_airflow_mcp/adapters/airflow_v3.py
astro_airflow_mcp/adapters/base.py
astro_airflow_mcp/cli/__init__.py
astro_airflow_mcp/cli/api.py
astro_airflow_mcp/cli/assets.py
astro_airflow_mcp/cli/config.py
astro_airflow_mcp/cli/context.py
astro_airflow_mcp/cli/dags.py
astro_airflow_mcp/cli/instances.py
astro_airflow_mcp/cli/main.py
astro_airflow_mcp/cli/output.py
astro_airflow_mcp/cli/runs.py
astro_airflow_mcp/cli/tasks.py
astro_airflow_mcp/config/__init__.py
astro_airflow_mcp/config/interpolation.py
astro_airflow_mcp/config/loader.py
astro_airflow_mcp/config/models.py
astro_airflow_mcp/tools/__init__.py
astro_airflow_mcp/tools/admin.py
astro_airflow_mcp/tools/asset.py
astro_airflow_mcp/tools/dag.py
astro_airflow_mcp/tools/dag_run.py
astro_airflow_mcp/tools/diagnostic.py
astro_airflow_mcp/tools/task.py
astro_airflow_mcp-0.4.0.dist-info/METADATA
astro_airflow_mcp-0.4.0.dist-info/WHEEL
astro_airflow_mcp-0.4.0.dist-info/entry_points.txt
astro_airflow_mcp-0.4.0.dist-info/licenses/LICENSE
astro_airflow_mcp-0.4.0.dist-info/RECORD
