Metadata-Version: 2.4
Name: astro-airflow-mcp
Version: 0.4.0
Summary: A FastMCP server for Airflow integration that can run standalone or as an Airflow 3 plugin
License-File: LICENSE
Requires-Python: >=3.10
Requires-Dist: fastmcp>=0.1.0
Requires-Dist: filelock>=3.0.0
Requires-Dist: httpx>=0.27.0
Requires-Dist: packaging>=21.0
Requires-Dist: pydantic>=2.0.0
Requires-Dist: pyyaml>=6.0
Requires-Dist: typer>=0.12.0
Provides-Extra: plugin
Requires-Dist: apache-airflow>=3.0.0; extra == 'plugin'
Requires-Dist: fastapi>=0.100.0; extra == 'plugin'
